LICENSE
README.md
setup.cfg
setup.py
tg_bot_ml/__init__.py
tg_bot_ml/img_bot.py
tg_bot_ml/table_bot.py
tg_bot_ml/tg_bot.py
tg_bot_ml/utils.py
tg_bot_ml.egg-info/PKG-INFO
tg_bot_ml.egg-info/SOURCES.txt
tg_bot_ml.egg-info/dependency_links.txt
tg_bot_ml.egg-info/requires.txt
tg_bot_ml.egg-info/top_level.txt