Metadata-Version: 2.1
Name: tg-bot-ml
Version: 0.0.10
Summary: Simple telegram bot for logging ML statistics.
Home-page: https://github.com/DmitryAsdre/telegram-ml-bot-stats.git
Download-URL: https://github.com/DmitryAsdre/telegram-ml-bot-stats/archive/refs/heads/main.zip
Author: Dmitry
Author-email: michalych2014@yandex.ru
License: GPLv3
Keywords: Telegram,Bot,ML,Machine Learning,Logger
Classifier: Development Status :: 3 - Alpha
Classifier: Intended Audience :: Developers
Classifier: Topic :: Software Development :: Build Tools
Classifier: Programming Language :: Python :: 3
Classifier: Programming Language :: Python :: 3.4
Classifier: Programming Language :: Python :: 3.5
Classifier: Programming Language :: Python :: 3.6
Classifier: Programming Language :: Python :: 3.7
Classifier: Programming Language :: Python :: 3.8
Classifier: Programming Language :: Python :: 3.9
Classifier: Programming Language :: Python :: 3.10
Classifier: Programming Language :: Python :: 3.11
License-File: LICENSE
